mr_streams/__init__.py
mr_streams/streamer.py
mr_streams/exceptions/__init__.py
mr_streams/exceptions/stream_exceptions.py
mr_streams-0.0.1.dist-info/LICENSE
mr_streams-0.0.1.dist-info/METADATA
mr_streams-0.0.1.dist-info/WHEEL
mr_streams-0.0.1.dist-info/top_level.txt
mr_streams-0.0.1.dist-info/RECORD
