Metadata-Version: 2.1
Name: mr-streams
Version: 0.0.1
Summary: an anti-pythonic map reduce utility
Home-page: https://github.com/pypa/sampleproject
Author: isConic
License: UNKNOWN
Platform: UNKNOWN
Classifier: Programming Language :: Python :: 3
Classifier: License :: OSI Approved :: MIT License
Classifier: Operating System :: OS Independent
